rnets/__init__.py
rnets/__main__.py
rnets/chemistry.py
rnets/conf_type_checker.py
rnets/dot.py
rnets/parser.py
rnets/struct.py
rnets/addons/__init__.py
rnets/addons/colorbar.py
rnets/colors/__init__.py
rnets/colors/colorschemes.py
rnets/colors/palettes.py
rnets/colors/utils.py
rnets/plotter/__init__.py
rnets/plotter/kinetic.py
rnets/plotter/thermo.py
rnets/plotter/utils.py
rNets-24.6.dist-info/LICENSE
rNets-24.6.dist-info/METADATA
rNets-24.6.dist-info/WHEEL
rNets-24.6.dist-info/entry_points.txt
rNets-24.6.dist-info/top_level.txt
rNets-24.6.dist-info/RECORD
