Metadata-Version: 2.1
Name: rNets
Version: 24.6
Summary: Rnets software for the visualization of reaction networks
Author: wvlab, Albert Sabadell-Rendón, Diego Garay-Ruiz
Author-email: Sergio Pablo-Garcia <spgarcica@gmail.com>, Raul Perez Soto <rperezsoto.research@gmail.com>
Maintainer-email: Sergio Pablo-Garcia <spgarcica@gmail.com>
License: MIT License
Project-URL: homepage, https://spgarcica.github.io/rNets/
Project-URL: repository, https://github.com/spgarcica/rNets
Keywords: dot,graphviz,reaction,networks,chemistry,reactivity
Classifier: Programming Language :: Python
Requires-Python: >=3.12
License-File: LICENSE
